package hjapp.com.umeng.analytics;

import android.content.Context;
import java.util.Map;

final class b$a extends Thread
{
  private final Object b = new Object();
  private Context c;
  private int d;
  private String e;
  private String f;
  private int g;
  private long h;
  private Map i;
  private String j;

  b$a(b paramb, Context paramContext, int paramInt)
  {
    this.c = paramContext;
    this.d = paramInt;
  }

  b$a(b paramb, Context paramContext, String paramString1, String paramString2, long paramLong, int paramInt1, int paramInt2)
  {
    this.c = paramContext;
    this.e = paramString1;
    this.f = paramString2;
    this.g = paramInt1;
    this.d = paramInt2;
    this.h = paramLong;
  }

  b$a(b paramb, Context paramContext, String paramString, Map paramMap, long paramLong, int paramInt)
  {
    this.c = paramContext;
    this.e = paramString;
    this.i = paramMap;
    this.d = paramInt;
    this.h = paramLong;
  }

  b$a(b paramb, Context paramContext, String paramString1, Map paramMap, String paramString2, int paramInt)
  {
    this.c = paramContext;
    this.e = paramString1;
    this.i = paramMap;
    this.j = paramString2;
    this.d = paramInt;
  }

  // ERROR //
  public final void run()
  {
    // Byte code:
    //   0: aload_0
    //   1: getfield 33	com/umeng/analytics/b$a:b	Ljava/lang/Object;
    //   4: astore_2
    //   5: aload_2
    //   6: monitorenter
    //   7: aload_0
    //   8: getfield 37	com/umeng/analytics/b$a:d	I
    //   11: istore 4
    //   13: iload 4
    //   15: ifne +63 -> 78
    //   18: aload_0
    //   19: getfield 35	com/umeng/analytics/b$a:c	Landroid/content/Context;
    //   22: ifnonnull +13 -> 35
    //   25: ldc 57
    //   27: ldc 59
    //   29: invokestatic 64	com/umeng/common/a:b	(Ljava/lang/String;Ljava/lang/String;)V
    //   32: aload_2
    //   33: monitorexit
    //   34: return
    //   35: aload_0
    //   36: getfield 25	com/umeng/analytics/b$a:a	Lcom/umeng/analytics/b;
    //   39: aload_0
    //   40: getfield 35	com/umeng/analytics/b$a:c	Landroid/content/Context;
    //   43: invokestatic 69	com/umeng/analytics/b:a	(Lcom/umeng/analytics/b;Landroid/content/Context;)V
    //   46: aload_2
    //   47: monitorexit
    //   48: return
    //   49: astore_3
    //   50: aload_2
    //   51: monitorexit
    //   52: aload_3
    //   53: athrow
    //   54: astore_1
    //   55: ldc 57
    //   57: ldc 71
    //   59: aload_1
    //   60: invokestatic 74	com/umeng/common/a:b	(Ljava/lang/String;Ljava/lang/String;Ljava/lang/Exception;)V
    //   63: return
    //   64: astore 5
    //   66: ldc 57
    //   68: ldc 59
    //   70: aload 5
    //   72: invokestatic 74	com/umeng/common/a:b	(Ljava/lang/String;Ljava/lang/String;Ljava/lang/Exception;)V
    //   75: goto -29 -> 46
    //   78: aload_0
    //   79: getfield 37	com/umeng/analytics/b$a:d	I
    //   82: iconst_1
    //   83: if_icmpne +17 -> 100
    //   86: aload_0
    //   87: getfield 25	com/umeng/analytics/b$a:a	Lcom/umeng/analytics/b;
    //   90: aload_0
    //   91: getfield 35	com/umeng/analytics/b$a:c	Landroid/content/Context;
    //   94: invokestatic 76	com/umeng/analytics/b:b	(Lcom/umeng/analytics/b;Landroid/content/Context;)V
    //   97: goto -51 -> 46
    //   100: aload_0
    //   101: getfield 37	com/umeng/analytics/b$a:d	I
    //   104: iconst_2
    //   105: if_icmpne +17 -> 122
    //   108: aload_0
    //   109: getfield 25	com/umeng/analytics/b$a:a	Lcom/umeng/analytics/b;
    //   112: aload_0
    //   113: getfield 35	com/umeng/analytics/b$a:c	Landroid/content/Context;
    //   116: invokestatic 78	com/umeng/analytics/b:c	(Lcom/umeng/analytics/b;Landroid/content/Context;)V
    //   119: goto -73 -> 46
    //   122: aload_0
    //   123: getfield 37	com/umeng/analytics/b$a:d	I
    //   126: iconst_3
    //   127: if_icmpne +33 -> 160
    //   130: aload_0
    //   131: getfield 25	com/umeng/analytics/b$a:a	Lcom/umeng/analytics/b;
    //   134: aload_0
    //   135: getfield 35	com/umeng/analytics/b$a:c	Landroid/content/Context;
    //   138: aload_0
    //   139: getfield 40	com/umeng/analytics/b$a:e	Ljava/lang/String;
    //   142: aload_0
    //   143: getfield 42	com/umeng/analytics/b$a:f	Ljava/lang/String;
    //   146: aload_0
    //   147: getfield 46	com/umeng/analytics/b$a:h	J
    //   150: aload_0
    //   151: getfield 44	com/umeng/analytics/b$a:g	I
    //   154: invokestatic 81	com/umeng/analytics/b:a	(Lcom/umeng/analytics/b;Landroid/content/Context;Ljava/lang/String;Ljava/lang/String;JI)V
    //   157: goto -111 -> 46
    //   160: aload_0
    //   161: getfield 37	com/umeng/analytics/b$a:d	I
    //   164: iconst_4
    //   165: if_icmpne +29 -> 194
    //   168: aload_0
    //   169: getfield 25	com/umeng/analytics/b$a:a	Lcom/umeng/analytics/b;
    //   172: aload_0
    //   173: getfield 35	com/umeng/analytics/b$a:c	Landroid/content/Context;
    //   176: aload_0
    //   177: getfield 40	com/umeng/analytics/b$a:e	Ljava/lang/String;
    //   180: aload_0
    //   181: getfield 49	com/umeng/analytics/b$a:i	Ljava/util/Map;
    //   184: aload_0
    //   185: getfield 46	com/umeng/analytics/b$a:h	J
    //   188: invokestatic 84	com/umeng/analytics/b:a	(Lcom/umeng/analytics/b;Landroid/content/Context;Ljava/lang/String;Ljava/util/Map;J)V
    //   191: goto -145 -> 46
    //   194: aload_0
    //   195: getfield 37	com/umeng/analytics/b$a:d	I
    //   198: iconst_5
    //   199: if_icmpne +29 -> 228
    //   202: aload_0
    //   203: getfield 25	com/umeng/analytics/b$a:a	Lcom/umeng/analytics/b;
    //   206: aload_0
    //   207: getfield 35	com/umeng/analytics/b$a:c	Landroid/content/Context;
    //   210: aload_0
    //   211: getfield 40	com/umeng/analytics/b$a:e	Ljava/lang/String;
    //   214: aload_0
    //   215: getfield 49	com/umeng/analytics/b$a:i	Ljava/util/Map;
    //   218: aload_0
    //   219: getfield 52	com/umeng/analytics/b$a:j	Ljava/lang/String;
    //   222: invokestatic 87	com/umeng/analytics/b:a	(Lcom/umeng/analytics/b;Landroid/content/Context;Ljava/lang/String;Ljava/util/Map;Ljava/lang/String;)V
    //   225: goto -179 -> 46
    //   228: aload_0
    //   229: getfield 37	com/umeng/analytics/b$a:d	I
    //   232: bipush 6
    //   234: if_icmpne -188 -> 46
    //   237: aload_0
    //   238: getfield 25	com/umeng/analytics/b$a:a	Lcom/umeng/analytics/b;
    //   241: aload_0
    //   242: getfield 35	com/umeng/analytics/b$a:c	Landroid/content/Context;
    //   245: aload_0
    //   246: getfield 40	com/umeng/analytics/b$a:e	Ljava/lang/String;
    //   249: aload_0
    //   250: getfield 52	com/umeng/analytics/b$a:j	Ljava/lang/String;
    //   253: invokestatic 90	com/umeng/analytics/b:a	(Lcom/umeng/analytics/b;Landroid/content/Context;Ljava/lang/String;Ljava/lang/String;)V
    //   256: goto -210 -> 46
    //
    // Exception table:
    //   from	to	target	type
    //   7	13	49	finally
    //   18	32	49	finally
    //   32	34	49	finally
    //   35	46	49	finally
    //   46	48	49	finally
    //   66	75	49	finally
    //   78	97	49	finally
    //   100	119	49	finally
    //   122	157	49	finally
    //   160	191	49	finally
    //   194	225	49	finally
    //   228	256	49	finally
    //   0	7	54	java/lang/Exception
    //   50	54	54	java/lang/Exception
    //   18	32	64	java/lang/Exception
    //   35	46	64	java/lang/Exception
  }
}

/* Location:           D:\tmp\沪江课件专用播放器\反编译工具包\jd-gui-0.3.5.windows\classes_dex2jar.jar
 * Qualified Name:     b.a
 * JD-Core Version:    0.6.2
 */