package hjapp.com.umeng.fb.a;

import hjapp.com.umeng.common.net.i;

public class a extends i
{
  private static final String a = a.class.getName();
  private static final int b = 30000;

  // ERROR //
  public c a(b paramb)
  {
    // Byte code:
    //   0: new 31	java/util/Random
    //   3: dup
    //   4: invokespecial 32	java/util/Random:<init>	()V
    //   7: sipush 1000
    //   10: invokevirtual 36	java/util/Random:nextInt	(I)I
    //   13: istore_2
    //   14: aload_1
    //   15: getfield 41	com/umeng/fb/a/b:f	Ljava/lang/String;
    //   18: astore_3
    //   19: aload_1
    //   20: getfield 44	com/umeng/fb/a/b:d	Ljava/lang/String;
    //   23: astore 4
    //   25: aload_1
    //   26: getfield 48	com/umeng/fb/a/b:e	Lorg/json/JSONObject;
    //   29: astore 5
    //   31: aload_1
    //   32: instanceof 38
    //   35: ifne +14 -> 49
    //   38: getstatic 19	com/umeng/fb/a/a:a	Ljava/lang/String;
    //   41: ldc 50
    //   43: invokestatic 55	android/util/Log:e	(Ljava/lang/String;Ljava/lang/String;)I
    //   46: pop
    //   47: aconst_null
    //   48: areturn
    //   49: aload_3
    //   50: invokevirtual 61	java/lang/String:length	()I
    //   53: iconst_1
    //   54: if_icmpgt +31 -> 85
    //   57: getstatic 19	com/umeng/fb/a/a:a	Ljava/lang/String;
    //   60: new 63	java/lang/StringBuilder
    //   63: dup
    //   64: invokespecial 64	java/lang/StringBuilder:<init>	()V
    //   67: iload_2
    //   68: invokevirtual 68	java/lang/StringBuilder:append	(I)Ljava/lang/StringBuilder;
    //   71: ldc 70
    //   73: invokevirtual 73	java/lang/StringBuilder:append	(Ljava/lang/String;)Ljava/lang/StringBuilder;
    //   76: invokevirtual 76	java/lang/StringBuilder:toString	()Ljava/lang/String;
    //   79: invokestatic 55	android/util/Log:e	(Ljava/lang/String;Ljava/lang/String;)I
    //   82: pop
    //   83: aconst_null
    //   84: areturn
    //   85: getstatic 19	com/umeng/fb/a/a:a	Ljava/lang/String;
    //   88: new 63	java/lang/StringBuilder
    //   91: dup
    //   92: invokespecial 64	java/lang/StringBuilder:<init>	()V
    //   95: iload_2
    //   96: invokevirtual 68	java/lang/StringBuilder:append	(I)Ljava/lang/StringBuilder;
    //   99: ldc 78
    //   101: invokevirtual 73	java/lang/StringBuilder:append	(Ljava/lang/String;)Ljava/lang/StringBuilder;
    //   104: aload_3
    //   105: invokevirtual 73	java/lang/StringBuilder:append	(Ljava/lang/String;)Ljava/lang/StringBuilder;
    //   108: ldc 80
    //   110: invokevirtual 73	java/lang/StringBuilder:append	(Ljava/lang/String;)Ljava/lang/StringBuilder;
    //   113: aload 5
    //   115: invokevirtual 83	org/json/JSONObject:toString	()Ljava/lang/String;
    //   118: invokevirtual 73	java/lang/StringBuilder:append	(Ljava/lang/String;)Ljava/lang/StringBuilder;
    //   121: invokevirtual 76	java/lang/StringBuilder:toString	()Ljava/lang/String;
    //   124: invokestatic 86	android/util/Log:i	(Ljava/lang/String;Ljava/lang/String;)I
    //   127: pop
    //   128: getstatic 19	com/umeng/fb/a/a:a	Ljava/lang/String;
    //   131: new 63	java/lang/StringBuilder
    //   134: dup
    //   135: invokespecial 64	java/lang/StringBuilder:<init>	()V
    //   138: iload_2
    //   139: invokevirtual 68	java/lang/StringBuilder:append	(I)Ljava/lang/StringBuilder;
    //   142: ldc 88
    //   144: invokevirtual 73	java/lang/StringBuilder:append	(Ljava/lang/String;)Ljava/lang/StringBuilder;
    //   147: aload_3
    //   148: invokevirtual 73	java/lang/StringBuilder:append	(Ljava/lang/String;)Ljava/lang/StringBuilder;
    //   151: invokevirtual 76	java/lang/StringBuilder:toString	()Ljava/lang/String;
    //   154: invokestatic 86	android/util/Log:i	(Ljava/lang/String;Ljava/lang/String;)I
    //   157: pop
    //   158: aload 4
    //   160: ifnull +264 -> 424
    //   163: new 90	java/util/ArrayList
    //   166: dup
    //   167: iconst_1
    //   168: invokespecial 93	java/util/ArrayList:<init>	(I)V
    //   171: astore 8
    //   173: aload 8
    //   175: new 95	org/apache/http/message/BasicNameValuePair
    //   178: dup
    //   179: aload 4
    //   181: aload 5
    //   183: invokevirtual 83	org/json/JSONObject:toString	()Ljava/lang/String;
    //   186: invokespecial 98	org/apache/http/message/BasicNameValuePair:<init>	(Ljava/lang/String;Ljava/lang/String;)V
    //   189: invokeinterface 104 2 0
    //   194: pop
    //   195: new 106	org/apache/http/client/entity/UrlEncodedFormEntity
    //   198: dup
    //   199: aload 8
    //   201: ldc 108
    //   203: invokespecial 111	org/apache/http/client/entity/UrlEncodedFormEntity:<init>	(Ljava/util/List;Ljava/lang/String;)V
    //   206: astore 10
    //   208: new 113	org/apache/http/client/methods/HttpPost
    //   211: dup
    //   212: aload_3
    //   213: invokespecial 116	org/apache/http/client/methods/HttpPost:<init>	(Ljava/lang/String;)V
    //   216: astore 11
    //   218: aload 11
    //   220: aload 10
    //   222: invokeinterface 122 1 0
    //   227: invokeinterface 128 2 0
    //   232: aload 11
    //   234: checkcast 113	org/apache/http/client/methods/HttpPost
    //   237: aload 10
    //   239: invokevirtual 132	org/apache/http/client/methods/HttpPost:setEntity	(Lorg/apache/http/HttpEntity;)V
    //   242: aload 11
    //   244: astore 12
    //   246: new 134	org/apache/http/impl/client/DefaultHttpClient
    //   249: dup
    //   250: invokespecial 135	org/apache/http/impl/client/DefaultHttpClient:<init>	()V
    //   253: astore 13
    //   255: aload 13
    //   257: invokeinterface 141 1 0
    //   262: astore 14
    //   264: aload 14
    //   266: sipush 30000
    //   269: invokestatic 147	org/apache/http/params/HttpConnectionParams:setConnectionTimeout	(Lorg/apache/http/params/HttpParams;I)V
    //   272: aload 14
    //   274: sipush 30000
    //   277: invokestatic 150	org/apache/http/params/HttpConnectionParams:setSoTimeout	(Lorg/apache/http/params/HttpParams;I)V
    //   280: aload 14
    //   282: ldc2_w 151
    //   285: invokestatic 158	org/apache/http/conn/params/ConnManagerParams:setTimeout	(Lorg/apache/http/params/HttpParams;J)V
    //   288: aload 13
    //   290: aload 12
    //   292: checkcast 160	org/apache/http/client/methods/HttpUriRequest
    //   295: invokeinterface 164 2 0
    //   300: astore 19
    //   302: aload 19
    //   304: invokeinterface 170 1 0
    //   309: invokeinterface 175 1 0
    //   314: sipush 200
    //   317: if_icmpne +156 -> 473
    //   320: aload 19
    //   322: invokeinterface 179 1 0
    //   327: invokestatic 184	org/apache/http/util/EntityUtils:toString	(Lorg/apache/http/HttpEntity;)Ljava/lang/String;
    //   330: astore 20
    //   332: ldc 186
    //   334: new 63	java/lang/StringBuilder
    //   337: dup
    //   338: ldc 188
    //   340: invokespecial 189	java/lang/StringBuilder:<init>	(Ljava/lang/String;)V
    //   343: aload 20
    //   345: invokevirtual 73	java/lang/StringBuilder:append	(Ljava/lang/String;)Ljava/lang/StringBuilder;
    //   348: invokevirtual 76	java/lang/StringBuilder:toString	()Ljava/lang/String;
    //   351: invokestatic 86	android/util/Log:i	(Ljava/lang/String;Ljava/lang/String;)I
    //   354: pop
    //   355: new 191	com/umeng/fb/a/c
    //   358: dup
    //   359: new 82	org/json/JSONObject
    //   362: dup
    //   363: aload 20
    //   365: invokespecial 192	org/json/JSONObject:<init>	(Ljava/lang/String;)V
    //   368: invokespecial 195	com/umeng/fb/a/c:<init>	(Lorg/json/JSONObject;)V
    //   371: astore 22
    //   373: aload 22
    //   375: areturn
    //   376: astore 17
    //   378: getstatic 19	com/umeng/fb/a/a:a	Ljava/lang/String;
    //   381: new 63	java/lang/StringBuilder
    //   384: dup
    //   385: invokespecial 64	java/lang/StringBuilder:<init>	()V
    //   388: iload_2
    //   389: invokevirtual 68	java/lang/StringBuilder:append	(I)Ljava/lang/StringBuilder;
    //   392: ldc 197
    //   394: invokevirtual 73	java/lang/StringBuilder:append	(Ljava/lang/String;)Ljava/lang/StringBuilder;
    //   397: aload_3
    //   398: invokevirtual 73	java/lang/StringBuilder:append	(Ljava/lang/String;)Ljava/lang/StringBuilder;
    //   401: invokevirtual 76	java/lang/StringBuilder:toString	()Ljava/lang/String;
    //   404: aload 17
    //   406: invokestatic 200	android/util/Log:d	(Ljava/lang/String;Ljava/lang/String;Ljava/lang/Throwable;)I
    //   409: pop
    //   410: aconst_null
    //   411: areturn
    //   412: astore 23
    //   414: new 202	java/lang/AssertionError
    //   417: dup
    //   418: aload 23
    //   420: invokespecial 205	java/lang/AssertionError:<init>	(Ljava/lang/Object;)V
    //   423: athrow
    //   424: new 207	org/apache/http/client/methods/HttpGet
    //   427: dup
    //   428: aload_3
    //   429: invokespecial 208	org/apache/http/client/methods/HttpGet:<init>	(Ljava/lang/String;)V
    //   432: astore 12
    //   434: goto -188 -> 246
    //   437: astore 15
    //   439: getstatic 19	com/umeng/fb/a/a:a	Ljava/lang/String;
    //   442: new 63	java/lang/StringBuilder
    //   445: dup
    //   446: invokespecial 64	java/lang/StringBuilder:<init>	()V
    //   449: iload_2
    //   450: invokevirtual 68	java/lang/StringBuilder:append	(I)Ljava/lang/StringBuilder;
    //   453: ldc 210
    //   455: invokevirtual 73	java/lang/StringBuilder:append	(Ljava/lang/String;)Ljava/lang/StringBuilder;
    //   458: aload_3
    //   459: invokevirtual 73	java/lang/StringBuilder:append	(Ljava/lang/String;)Ljava/lang/StringBuilder;
    //   462: invokevirtual 76	java/lang/StringBuilder:toString	()Ljava/lang/String;
    //   465: aload 15
    //   467: invokestatic 200	android/util/Log:d	(Ljava/lang/String;Ljava/lang/String;Ljava/lang/Throwable;)I
    //   470: pop
    //   471: aconst_null
    //   472: areturn
    //   473: aconst_null
    //   474: areturn
    //
    // Exception table:
    //   from	to	target	type
    //   288	373	376	org/apache/http/client/ClientProtocolException
    //   195	208	412	java/io/UnsupportedEncodingException
    //   288	373	437	java/lang/Exception
  }
}

/* Location:           D:\tmp\沪江课件专用播放器\反编译工具包\jd-gui-0.3.5.windows\classes_dex2jar.jar
 * Qualified Name:     aersion:    0.6.2
 */